libhwp-0.2.0.dist-info/METADATA
libhwp-0.2.0.dist-info/WHEEL
libhwp/__init__.py
libhwp/libhwp.cp38-win_amd64.pyd
libhwp-0.2.0.dist-info/RECORD
