Metadata-Version: 2.1
Name: libhwp
Version: 0.2.0
Classifier: Programming Language :: Rust
Classifier: Programming Language :: Python :: Implementation :: CPython
Classifier: Programming Language :: Python :: Implementation :: PyPy
License: Apache-2.0
Requires-Python: >=3.7
